lowatt_enedis/__init__.py
lowatt_enedis/__main__.py
lowatt_enedis/certauth.py
lowatt_enedis/decrypt.py
lowatt_enedis/services.py
lowatt_enedis/wsdl/CommandeAccesDonneesMesures/Services/CommanderAccesDonneesMesures/CommanderAccesDonneesMesures-V1.0.wsdl
lowatt_enedis/wsdl/CommandeAccesDonneesMesures/Services/CommanderAccesDonneesMesures/CommanderAccesDonneesMesures-V1.0.xsd
lowatt_enedis/wsdl/CommandeAccesDonneesMesures/Services/CommanderAccesDonneesMesures/ENEDIS.Dictionnaire.Technique.v1.0.xsd
lowatt_enedis/wsdl/CommandeAccesDonneesMesures/Services/CommanderAccesDonneesMesures/ENEDIS.Dictionnaire.TypeComplexe.v5.0.xsd
lowatt_enedis/wsdl/CommandeAccesDonneesMesures/Services/CommanderAccesDonneesMesures/ENEDIS.Dictionnaire.TypeSimple.v5.0.xsd
lowatt_enedis/wsdl/CommandeAccesDonneesMesures/Services/CommanderAccesDonneesMesures/W3C.SoapEnv.xsd
lowatt_enedis/wsdl/CommandeArretServiceSouscritMesures/Dictionnaires/Metier/v5.0/ENEDIS.Dictionnaire.TypeComplexe.v5.0.xsd
lowatt_enedis/wsdl/CommandeArretServiceSouscritMesures/Dictionnaires/Metier/v5.0/ENEDIS.Dictionnaire.TypeSimple.v5.0.xsd
lowatt_enedis/wsdl/CommandeArretServiceSouscritMesures/Dictionnaires/Technique/W3C.SoapEnv.xsd
lowatt_enedis/wsdl/CommandeArretServiceSouscritMesures/Dictionnaires/Technique/v1.0/ENEDIS.Dictionnaire.Technique.v1.0.xsd
lowatt_enedis/wsdl/CommandeArretServiceSouscritMesures/Services/CommandeArretServiceSouscritMesures/CommandeArretServiceSouscritMesures-v1.0.wsdl
lowatt_enedis/wsdl/CommandeArretServiceSouscritMesures/Services/CommandeArretServiceSouscritMesures/CommanderArretServiceSouscritMesures-v1.0.xsd
lowatt_enedis/wsdl/CommandeCollectePublicationMesures/Dictionnaires/Metier/v5.0/ENEDIS.Dictionnaire.TypeComplexe.v5.0.xsd
lowatt_enedis/wsdl/CommandeCollectePublicationMesures/Dictionnaires/Metier/v5.0/ENEDIS.Dictionnaire.TypeSimple.v5.0.xsd
lowatt_enedis/wsdl/CommandeCollectePublicationMesures/Dictionnaires/Technique/W3C.SoapEnv.xsd
lowatt_enedis-3.2.0.dist-info/METADATA
lowatt_enedis-3.2.0.dist-info/WHEEL
lowatt_enedis-3.2.0.dist-info/entry_points.txt
lowatt_enedis-3.2.0.dist-info/licenses/COPYING
lowatt_enedis-3.2.0.dist-info/RECORD
