Metadata-Version: 2.4
Name: lowatt-enedis
Version: 3.2.0
Summary: Python client for Enedis SGE web-service
Project-URL: Source, https://github.com/lowatt/lowatt-enedis
Project-URL: Tracker, https://github.com/lowatt/lowatt-enedis/issues
Author-email: Lowatt <info@lowatt.fr>
License: GPLv3
License-File: COPYING
Classifier: Development Status :: 5 - Production/Stable
Classifier: Environment :: Console
Classifier: License :: OSI Approved :: GNU General Public License v3 (GPLv3)
Classifier: Operating System :: OS Independent
Classifier: Programming Language :: Python :: 3
Classifier: Programming Language :: Python :: 3 :: Only
Classifier: Programming Language :: Python :: 3.9
Classifier: Programming Language :: Python :: 3.10
Classifier: Programming Language :: Python :: 3.11
Classifier: Topic :: System :: Archiving :: Mirroring
Requires-Python: >=3.9
Requires-Dist: certifi
Requires-Dist: rich
Requires-Dist: suds-py3
Provides-Extra: cryptography
Requires-Dist: cryptography; extra == 'cryptography'
Provides-Extra: test
Requires-Dist: freezegun; extra == 'test'
Requires-Dist: importlib-metadata; (python_version < '3.10') and extra == 'test'
Requires-Dist: lxml; extra == 'test'
Requires-Dist: pytest; extra == 'test'
Requires-Dist: pytest-accept; extra == 'test'
Requires-Dist: pytest-cov; extra == 'test'
Requires-Dist: pyyaml; extra == 'test'
Provides-Extra: typing
Requires-Dist: mypy; extra == 'typing'
Requires-Dist: types-freezegun; extra == 'typing'
Requires-Dist: types-pyyaml; extra == 'typing'
